{
  "scenario": "1775 to 1780; Long Duration",
  "campaign_year": 1775,
  "resources": {
    "BRITISH": 6,
    "PATRIOTS": 3,
    "FRENCH": 5,
    "INDIANS": 0
  },
  "fni_level": 0,
  "toa_played": false,
"leaders": {
  "WASHINGTON":      "Pennsylvania",
  "GAGE":            null,
  "HOWE":            null,
  "CLINTON":         "New_York_City",

  "ROCHAMBEAU":      null,
  "LAUZUN":          null,

  "BRANT":           "Northwest",
  "CORNPLANTER":     "Pennsylvania",
  "DRAGGING_CANOE":  "Southwest"
},
  "bs_played": {
    "BRITISH": false,
    "PATRIOTS": false,
    "INDIANS": false,
    "FRENCH": false
  },
  "casualties": {
    "BRITISH": 0,
    "PATRIOTS": 0
  },
  "unavailable": {
    "FRENCH_REGULARS": 4,
    "FRENCH_SQUADRONS": 0
  },
  "current_event": "Card_038",
  "upcoming_event": "Card_100",
  "deck": [
    "Card_100",
    "Card_039",
    "Card_001",
    "Card_075",
    "Card_103",
    "Card_076",
    "Card_048",
    "Card_067",
    "Card_050",
    "Card_090",
    "Card_073",
    "Card_014",
    "Card_088",
    "Card_056",
    "Card_008",
    "Card_077",
    "Card_099",
    "Card_013",
    "Card_012",
    "Card_106",
    "Card_022",
    "Card_011",
    "Card_046",
    "Card_082",
    "Card_102",
    "Card_036",
    "Card_021",
    "Card_040",
    "Card_080",
    "Card_002",
    "Card_057",
    "Card_007",
    "Card_092",
    "Card_058",
    "Card_018",
    "Card_060",
    "Card_105",
    "Card_091",
    "Card_023",
    "Card_027",
    "Card_079",
    "Card_107",
    "Card_098",
    "Card_095",
    "Card_064",
    "Card_035",
    "Card_108",
    "Card_096",
    "Card_062",
    "Card_006",
    "Card_066",
    "Card_109",
    "Card_083",
    "Card_094",
    "Card_009",
    "Card_087",
    "Card_053",
    "Card_059",
    "Card_030",
    "Card_063",
    "Card_086",
    "Card_110",
    "Card_025",
    "Card_005",
    "Card_028",
    "Card_033",
    "Card_069",
    "Card_089",
    "Card_084",
    "Card_034",
    "Card_015",
    "Card_017",
    "Card_041",
    "Card_003",
    "Card_061",
    "Card_029",
    "Card_024",
    "Card_065",
    "Card_047",
    "Card_093",
    "Card_051",
    "Card_019",
    "Card_045",
    "Card_085",
    "Card_074",
    "Card_004",
    "Card_010",
    "Card_104",
    "Card_026",
    "Card_052"
  ],
  "eligible_order": [
    "PATRIOTS",
    "INDIANS",
    "BRITISH",
    "FRENCH"
  ],
  "spaces": {
    "Quebec_City": {
      "British_Regulars": 1,
      "British_Tory": 1,
      "British_Fort": 1,
      "Patriot_Continentals": 0,
      "Patriot_Militia": 1,
      "Patriot_Fort": 0,
      "Indian_War_Party": 1,
      "Indian_Village": 1,
      "French_Regulars": 0,
      "French_Squadron": 0,
      "Support": 2,
      "Opposition": 0
    },
    "Quebec": {
      "British_Regulars": 1,
      "British_Tory": 2,
      "British_Fort": 1,
      "Patriot_Continentals": 0,
      "Patriot_Militia": 0,
      "Patriot_Fort": 0,
      "Indian_War_Party": 1,
      "Indian_Village": 1,
      "French_Regulars": 0,
      "French_Squadron": 0,
      "Support": 2,
      "Opposition": 0
    },
    "New_Hampshire": {
      "British_Regulars": 0,
      "British_Tory": 3,
      "British_Fort": 0,
      "Patriot_Continentals": 0,
      "Patriot_Militia": 0,
      "Patriot_Fort": 0,
      "Indian_War_Party": 0,
      "Indian_Village": 0,
      "French_Regulars": 0,
      "French_Squadron": 0,
      "Support": 1,
      "Opposition": 0
    },
    "Massachusetts": {
      "British_Regulars": 0,
      "British_Tory": 1,
      "British_Fort": 0,
      "Patriot_Continentals": 1,
      "Patriot_Militia": 1,
      "Patriot_Fort": 1,
      "Indian_War_Party": 0,
      "Indian_Village": 0,
      "French_Regulars": 0,
      "French_Squadron": 0,
      "Support": 2,
      "Opposition": 0
    },
    "Boston": {
      "British_Regulars": 3,
      "British_Tory": 0,
      "British_Fort": 1,
      "Patriot_Continentals": 0,
      "Patriot_Militia": 0,
      "Patriot_Fort": 0,
      "Indian_War_Party": 0,
      "Indian_Village": 0,
      "French_Regulars": 0,
      "French_Squadron": 0,
      "Support": 1,
      "Opposition": 0
    },
    "Connecticut_Rhode_Island": {},
    "New_York_City": {
      "British_Regulars": 1,
      "British_Tory": 1,
      "British_Fort": 0,
      "Patriot_Continentals": 0,
      "Patriot_Militia": 0,
      "Patriot_Fort": 0,
      "Indian_War_Party": 0,
      "Indian_Village": 0,
      "French_Regulars": 0,
      "French_Squadron": 0,
      "Support": 1,
      "Opposition": 0
    },
    "New_York": {
      "British_Regulars": 3,
      "British_Tory": 3,
      "British_Fort": 0,
      "Patriot_Continentals": 3,
      "Patriot_Militia": 1,
      "Patriot_Fort": 0,
      "Indian_War_Party": 2,
      "Indian_Village": 1,
      "French_Regulars": 0,
      "French_Squadron": 0,
      "Support": 3,
      "Opposition": 0
    },
    "New_Jersey": {
      "British_Regulars": 0,
      "British_Tory": 0,
      "British_Fort": 0,
      "Patriot_Continentals": 2,
      "Patriot_Militia": 4,
      "Patriot_Fort": 0,
      "Indian_War_Party": 0,
      "Indian_Village": 0,
      "French_Regulars": 0,
      "French_Squadron": 0,
      "Support": 1,
      "Opposition": 0
    },
    "Philadelphia": {
      "British_Regulars": 0,
      "British_Tory": 3,
      "British_Fort": 0,
      "Patriot_Continentals": 0,
      "Patriot_Militia": 1,
      "Patriot_Fort": 0,
      "Indian_War_Party": 0,
      "Indian_Village": 0,
      "French_Regulars": 0,
      "French_Squadron": 0,
      "Support": 1,
      "Opposition": 0
    },
    "Pennsylvania": {
      "British_Regulars": 0,
      "British_Tory": 1,
      "British_Fort": 0,
      "Patriot_Continentals": 5,
      "Patriot_Militia": 2,
      "Patriot_Fort": 1,
      "Indian_War_Party": 1,
      "Indian_Village": 0,
      "French_Regulars": 0,
      "French_Squadron": 0,
      "Support": 1,
      "Opposition": 0
    },
    "Maryland-Delaware": {},
    "Norfolk": {
      "British_Regulars": 1,
      "British_Tory": 1,
      "British_Fort": 0,
      "Patriot_Continentals": 0,
      "Patriot_Militia": 0,
      "Patriot_Fort": 0,
      "Indian_War_Party": 0,
      "Indian_Village": 0,
      "French_Regulars": 0,
      "French_Squadron": 0,
      "Support": 1,
      "Opposition": 0
    },
    "Virginia": {
      "British_Regulars": 0,
      "British_Tory": 2,
      "British_Fort": 0,
      "Patriot_Continentals": 0,
      "Patriot_Militia": 0,
      "Patriot_Fort": 0,
      "Indian_War_Party": 0,
      "Indian_Village": 0,
      "French_Regulars": 0,
      "French_Squadron": 0,
      "Support": 1,
      "Opposition": 0
    },
    "North_Carolina": {
      "British_Regulars": 0,
      "British_Tory": 1,
      "British_Fort": 0,
      "Patriot_Continentals": 0,
      "Patriot_Militia": 2,
      "Patriot_Fort": 0,
      "Indian_War_Party": 0,
      "Indian_Village": 0,
      "French_Regulars": 0,
      "French_Squadron": 0,
      "Support": 1,
      "Opposition": 0
    },
    "South_Carolina": {
      "British_Regulars": 0,
      "British_Tory": 0,
      "British_Fort": 0,
      "Patriot_Continentals": 0,
      "Patriot_Militia": 2,
      "Patriot_Fort": 0,
      "Indian_War_Party": 1,
      "Indian_Village": 1,
      "French_Regulars": 0,
      "French_Squadron": 0,
      "Support": 1,
      "Opposition": 0
    },
    "Charles_Town": {
      "British_Regulars": 0,
      "British_Tory": 1,
      "British_Fort": 0,
      "Patriot_Continentals": 2,
      "Patriot_Militia": 2,
      "Patriot_Fort": 1,
      "Indian_War_Party": 0,
      "Indian_Village": 0,
      "French_Regulars": 0,
      "French_Squadron": 0,
      "Support": 2,
      "Opposition": 0
    },
    "Savannah": {
      "British_Regulars": 1,
      "British_Tory": 1,
      "British_Fort": 0,
      "Patriot_Continentals": 0,
      "Patriot_Militia": 0,
      "Patriot_Fort": 0,
      "Indian_War_Party": 0,
      "Indian_Village": 0,
      "French_Regulars": 0,
      "French_Squadron": 0,
      "Support": 1,
      "Opposition": 0
    },
    "Georgia": {
      "British_Regulars": 0,
      "British_Tory": 0,
      "British_Fort": 0,
      "Patriot_Continentals": 0,
      "Patriot_Militia": 1,
      "Patriot_Fort": 0,
      "Indian_War_Party": 0,
      "Indian_Village": 0,
      "French_Regulars": 0,
      "French_Squadron": 0,
      "Support": 1,
      "Opposition": 0
    },
    "Northwest": {
      "British_Regulars": 0,
      "British_Tory": 1,
      "British_Fort": 0,
      "Patriot_Continentals": 0,
      "Patriot_Militia": 0,
      "Patriot_Fort": 0,
      "Indian_War_Party": 2,
      "Indian_Village": 1,
      "French_Regulars": 0,
      "French_Squadron": 0,
      "Support": 0,
      "Opposition": 0
    },
    "Southwest": {
      "British_Regulars": 0,
      "British_Tory": 0,
      "British_Fort": 0,
      "Patriot_Continentals": 0,
      "Patriot_Militia": 0,
      "Patriot_Fort": 0,
      "Indian_War_Party": 1,
      "Indian_Village": 1,
      "French_Regulars": 0,
      "French_Squadron": 0,
      "Support": 0,
      "Opposition": 0
    },
    "Florida": {
      "British_Regulars": 1,
      "British_Tory": 0,
      "British_Fort": 1,
      "Patriot_Continentals": 0,
      "Patriot_Militia": 0,
      "Patriot_Fort": 0,
      "Indian_War_Party": 1,
      "Indian_Village": 1,
      "French_Regulars": 0,
      "French_Squadron": 0,
      "Support": 1,
      "Opposition": 0
    }
  },
  "brit_support_total": 27,
  "opposition_total": 0,
  "loyalist_pieces": 33
}
